CHANGES.txt
LICENSE.GPL
LICENSE.txt
README.txt
ZopePublicLicense.txt
setup.py
plone/__init__.py
plone.relations.egg-info/PKG-INFO
plone.relations.egg-info/SOURCES.txt
plone.relations.egg-info/dependency_links.txt
plone.relations.egg-info/namespace_packages.txt
plone.relations.egg-info/not-zip-safe
plone.relations.egg-info/requires.txt
plone.relations.egg-info/top_level.txt
plone/relations/README.txt
plone/relations/__init__.py
plone/relations/configure.zcml
plone/relations/container.py
plone/relations/container.txt
plone/relations/interfaces.py
plone/relations/lazylist.py
plone/relations/relationships.py
plone/relations/tests.py