Metadata-Version: 1.0
Name: plone.relations
Version: 2.0
Summary: Tools for defining and querying complex relationships between objects
Home-page: http://pypi.python.org/pypi/plone.relations
Author: Alec Mitchell
Author-email: apm13@columbia.edu
License: GPL with container.txt covered by ZPL and owned by Zope Corp.
Keywords: references relationships plone
Platform: UNKNOWN
Classifier: Framework :: Plone
Classifier: Framework :: Zope2
